Metadata-Version: 1.1
Name: saumyasha
Version: 0.0.1
Summary: A basic text logger
Home-page: UNKNOWN
Author: Saumya Shah
Author-email: saumya.shah@utsa.edu
License: MIT
Keywords: logger
Platform: UNKNOWN
Classifier: Development Status :: 5 - Production/Stable
Classifier: Intended Audience :: Education
Classifier: Operating System :: Microsoft :: Windows :: Windows 10
Classifier: License :: OSI Approved :: MIT License
Classifier: Programming Language :: Python :: 3
